hgtools/__init__.py
hgtools/managers/__init__.py
hgtools/managers/base.py
hgtools/managers/cmd.py
hgtools/managers/library.py
hgtools/managers/reentry.py
hgtools/managers/subprocess.py
hgtools-10.1.0.dist-info/LICENSE
hgtools-10.1.0.dist-info/METADATA
hgtools-10.1.0.dist-info/WHEEL
hgtools-10.1.0.dist-info/top_level.txt
hgtools-10.1.0.dist-info/RECORD
